MANIFEST.in
README.md
requirements.txt
setup.cfg
setup.py
graphspace_python/__init__.py
graphspace_python.egg-info/PKG-INFO
graphspace_python.egg-info/SOURCES.txt
graphspace_python.egg-info/dependency_links.txt
graphspace_python.egg-info/not-zip-safe
graphspace_python.egg-info/requires.txt
graphspace_python.egg-info/top_level.txt
graphspace_python/api/__init__.py
graphspace_python/api/client.py
graphspace_python/api/config.py
graphspace_python/api/errors.py
graphspace_python/api/endpoint/__init__.py
graphspace_python/api/endpoint/graphs.py
graphspace_python/api/endpoint/groups.py
graphspace_python/api/endpoint/layouts.py
graphspace_python/api/obj/__init__.py
graphspace_python/api/obj/api_response.py
graphspace_python/api/obj/graph.py
graphspace_python/api/obj/group.py
graphspace_python/api/obj/layout.py
graphspace_python/api/obj/member.py
graphspace_python/api/obj/response_object.py
graphspace_python/graphs/__init__.py
graphspace_python/graphs/classes/__init__.py
graphspace_python/graphs/classes/gsgraph.py
graphspace_python/graphs/classes/gsgroup.py
graphspace_python/graphs/classes/gslayout.py
graphspace_python/graphs/classes/gslegend.py
graphspace_python/graphs/formatter/__init__.py
graphspace_python/graphs/formatter/json_formatter.py
tests/__init__.py
tests/errors_test.py
tests/graphs_test.py
tests/groups_test.py
tests/layouts_test.py
tests/legend_test.py