Metadata-Version: 1.1
Name: graphspace-python
Version: 1.3.0
Summary: Python client for GraphSpace REST API
Home-page: http://github.com/adbharadwaj/graphspace-python
Author: Aditya Bharadwaj
Author-email: adb@vt.edu
License: GPL3
Platform: UNKNOWN
Classifier: Intended Audience :: Developers
Classifier: Intended Audience :: Science/Research
Classifier: Operating System :: OS Independent
Classifier: Topic :: Scientific/Engineering
Classifier: Environment :: Web Environment
Classifier: Programming Language :: Python :: 2.6
Classifier: Programming Language :: Python :: 2.7
Classifier: Programming Language :: Python :: 3.2
Classifier: Programming Language :: Python :: 3.3
Classifier: Programming Language :: Python :: 3.4
Classifier: License :: OSI Approved :: GNU General Public License (GPL)
